setup.cfg
setup.py
dist_mymod1v2KLQ/mymod1v2KLQ.py
mymod1v2KLQ.egg-info/PKG-INFO
mymod1v2KLQ.egg-info/SOURCES.txt
mymod1v2KLQ.egg-info/dependency_links.txt
mymod1v2KLQ.egg-info/not-zip-safe
mymod1v2KLQ.egg-info/top_level.txt