Metadata-Version: 1.0
Name: mymod1v2KLQ
Version: 0.1
Summary: None discription
Home-page: UNKNOWN
Author: UNKNOWN
Author-email: kolyaleonof@yandex.ru
License: UNKNOWN
Platform: UNKNOWN
